evdschat/__init__.py
evdschat/common/__init__.py
evdschat/common/akeys.py
evdschat/common/bridge.py
evdschat/common/github_actions.py
evdschat/common/globals.py
evdschat/core/__init__.py
evdschat/core/builder.py
evdschat/core/chat.py
evdschat/core/result.py
evdschat/model/__init__.py
evdschat/model/chatters.py
evdschat/src/getter.c
evdschat-0.1.10.dist-info/METADATA
evdschat-0.1.10.dist-info/WHEEL
evdschat-0.1.10.dist-info/licenses/LICENSE
evdschat-0.1.10.dist-info/RECORD
