Metadata-Version: 2.3
Name: evdschat
Version: 0.1.10
Summary: evdschat is an open-source Python package designed to enhance the evdspy package by allowing users to interact with the evdschat Application. This Node.js project aims to provide the most specific and accurate data users request during conversations, based on arguments such as start date, end date, and aggregation type, as described in the evdspy.
Project-URL: repository, https://github.com/SermetPekin/evdschat
Author-email: Sermet Pekin <Sermet.Pekin@gmail.com>
License: Creative Commons Attribution-NonCommercial 4.0 International Public License
Keywords: API,CBRT,Generative AI,Node.js,Python,TCMB,chatbot,data-aggregation,evdschat,evdspy,open-source
Requires-Python: >=3.10
Requires-Dist: evdspy>=1.1.40
Requires-Dist: pydantic>=2.9.1
Requires-Dist: rich>=13.8.1
